Metadata-Version: 2.1
Name: 3301-calc
Version: 0.0.1
Summary: Python command line application bare bones template.
Author: Anurag Kumar Singh
Author-email: anurag3301.0x0@gmail.com
